AUTHORS
CHANGES
LICENSE
MANIFEST.in
README
VERSION
requirements.txt
setup.py
httpproxy/__init__.py
httpproxy/cache.py
httpproxy/crawler.py
httpproxy/data.py
httpproxy/ping.py
httpproxy/settings.py
httpproxy.egg-info/PKG-INFO
httpproxy.egg-info/SOURCES.txt
httpproxy.egg-info/dependency_links.txt
httpproxy.egg-info/pbr.json
httpproxy.egg-info/requires.txt
httpproxy.egg-info/top_level.txt