Metadata-Version: 1.0
Name: httpproxy
Version: 0.5
Summary: httpproxy
Home-page: https://github.com/lvjiyong/httpproxy
Author: lvjiyong
Author-email: lvjiyong@gmail.com
License: GPL
Platform: any
